LICENSE
MANIFEST.in
README
setup.py
delayedblocks/__init__.py
delayedblocks/models.py
delayedblocks/templatetags.py
django_delayedblocks.egg-info/PKG-INFO
django_delayedblocks.egg-info/SOURCES.txt
django_delayedblocks.egg-info/dependency_links.txt
django_delayedblocks.egg-info/not-zip-safe
django_delayedblocks.egg-info/top_level.txt