Metadata-Version: 1.0
Name: django-delayedblocks
Version: 0.0.1
Summary: Django Delayed Blocks
Home-page: http://github.com/ojii/django-delayedblocks
Author: Jonas Obrist
Author-email: jonas.obrist@divio.ch
License: UNKNOWN
Platform: UNKNOWN
